docker_games/__init__.py
docker_games/client.py
docker_games/exceptions.py
docker_games/network.py
docker_games/servers.py
docker_games/validators.py
docker_games/volumes.py
tests/__init__.py
tests/conftest.py
tests/test_client.py
tests/test_network.py
tests/test_servers.py
tests/test_validators.py
docker_games-1.0.0a5.dist-info/LICENSE
docker_games-1.0.0a5.dist-info/METADATA
docker_games-1.0.0a5.dist-info/WHEEL
docker_games-1.0.0a5.dist-info/top_level.txt
docker_games-1.0.0a5.dist-info/RECORD
