Metadata-Version: 2.1
Name: docker-games
Version: 1.0.0a5
Summary: Easily create game servers using Docker and Python.
Home-page: https://github.com/StefanoFrazzetto/DockerGameServers
Author: Stefano Frazzetto
Author-email: stefano+docker_games@hey.com
License: Apache-2.0
Project-URL: Bug Reports, https://github.com/StefanoFrazzetto/DockerGameServers/issues
Project-URL: Source, https://github.com/StefanoFrazzetto/DockerGameServers
Keywords: automation,game,multiplayer,server,cloud
Platform: UNKNOWN
Classifier: Development Status :: 3 - Alpha
Classifier: Programming Language :: Python :: 3
Classifier: Programming Language :: Python :: 3.6
Classifier: Programming Language :: Python :: 3.7
Classifier: Programming Language :: Python :: 3.8
Classifier: Programming Language :: Python :: 3.9
Classifier: License :: OSI Approved :: Apache Software License
Classifier: Operating System :: OS Independent
Classifier: Topic :: Games/Entertainment
Classifier: Topic :: Communications :: Conferencing
Classifier: Topic :: Software Development :: Libraries
Requires-Python: >=3.6
Requires-Dist: docker
Provides-Extra: test
Requires-Dist: pytest ; extra == 'test'
